{"FAVORITES":[{"name":"NRK1 HD"},{"name":"NRK1 HEVC"},{"name":"NRK2 HD"},{"name":"NRK2 HEVC"},{"name":"NRK SUPER / NRK3 HD"},{"name":"NRK SUPER / NRK3 HEVC"},{"name":"TV 2 HD"},{"name":"TV 2 HEVC"},{"name":"TVNORGE HD"},{"name":"TVNORGE HEVC"},{"name":"TV 2 LIVSSTIL HD"},{"name":"TV 2 LIVSSTIL HEVC"},{"name":"TV 2 ZEBRA HD"},{"name":"TV 2 ZEBRA HEVC"},{"name":"TV 2 NYHETSKANALEN HD"},{"name":"TV 2 NYHETSKANALEN HEVC"},{"name":"TV3 HD"},{"name":"TV3 HEVC"},{"name":"VIASAT 4 HD"},{"name":"VIASAT 4 FHD"},{"name":"MAX HD"},{"name":"MAX HEVC"},{"name":"TLC NORGE HD"},{"name":"TLC NORGE HEVC"},{"name":"TV6"},{"name":"KANAL 10"},{"name":"VOX HD"},{"name":"VOX HEVC"},{"name":"FEM HD"},{"name":"FEM HEVC"},{"name":"MATKANALEN"},{"name":"VGTV HD"},{"name":"VGTV HEVC"},{"name":"NRK1 NORDNYTT HD"},{"name":"NRK1 NORDLAND HD"},{"name":"NRK1 MIDTNYTT HD"},{"name":"NRK1 VESTLANDSREVYEN HD"},{"name":"NRK1 ROGALAND HD"},{"name":"NRK1 VESTFOLD OG TELEMARK HD"},{"name":"NRK1 INNLANDET HD"}],"KIDS":[{"name":"DISNEY CHANNEL"},{"name":"NICKTOONS"},{"name":"NICKELODEON"},{"name":"BOOMERANG"},{"name":"CARTOON NETWORK"},{"name":"DISNEY JUNIOR"},{"name":"NICK JR."}],"MOVIES":[{"name":"C MORE FIRST HD"},{"name":"C MORE HITS HD"},{"name":"C MORE SERIES HD"},{"name":"C MORE STARS HD"},{"name":"V FILM ACTION HD"},{"name":"V FILM HITS HD"},{"name":"V FILM PREMIERE HD"},{"name":"VIASAT SERIES HD"},{"name":"VIASAT FILM FAMILY"},{"name":"SF KANALEN"}],"FACTS DOCUMENTARY":[{"name":"NAT GEO HD"},{"name":"NAT GEO WILD HD"},{"name":"DISCOVERY HD"},{"name":"VISJON NORGE HD"},{"name":"VISJON NORGE HEVC"},{"name":"DISCOVERY SCIENCE"},{"name":"ID INVESTIGATION DISCOVERY"},{"name":"BBC EARTH HD"},{"name":"BBC BRIT HD"},{"name":"BBC BRIT HEVC"},{"name":"ANIMAL PLANET HD"},{"name":"HISTORY HD"},{"name":"HISTORY2 HD"},{"name":"VIASAT HISTORY HD"},{"name":"VIASAT NATURE HD"}],"MUSIC":[{"name":"BLOOMBERG"},{"name":"MTV HD"},{"name":"MTV 80S HD"},{"name":"CNN INTERNATIONAL"},{"name":"BBC WORLD NEWS HD"}],"SPORTS":[{"name":"VIASAT SPORT ULTRA"},{"name":"VIASAT SPORT ULTRA HD"},{"name":"V SPORT ULTRA HEVC FHD"},{"name":"V SPORT ULTRA HEVC 4K"},{"name":"TV 2 SPORT 1 HD"},{"name":"TV 2 SPORT 1 HEVC"},{"name":"TV 2 SPORT 2 HD"},{"name":"TV 2 SPORT 2 HEVC"},{"name":"TV2 SPORT PREMIUM HD"},{"name":"TV 2 SPORT PREMIUM HD (BK)"},{"name":"TV2 SPORT PREMIUM 2 HD"},{"name":"TV 2 SPORT PREMIUM 2 HD (BK)"},{"name":"MOTORVISION TV HEVC"},{"name":"MOTORVISION TV HD"},{"name":"EUROSPORT 1 HD"},{"name":"EUROSPORT 1 HEVC"},{"name":"EUROSPORT NORGE HD"},{"name":"EUROSPORT NORGE HEVC"},{"name":"EUROSPORT PLUSS 1 HD"},{"name":"EUROSPORT PLUSS 2 HD"},{"name":"EUROSPORT PLUSS 3 HD"},{"name":"EUROSPORT PLUSS 4 HD"},{"name":"EUROSPORT PLUSS 5 HD"},{"name":"EURO SPORT PLUSS 6 HD"},{"name":"EURO SPORT PLUSS 7 HD"},{"name":"EURO SPORT PLUSS 8 HD"},{"name":"EURO SPORT PLUSS 9 HD"},{"name":"EURO SPORT PLUSS 10 HD"},{"name":"EURO SPORT PLUSS 11 HD"},{"name":"EURO SPORT PLUSS 12 HD"},{"name":"VIASPORT+ HD"},{"name":"VIASPORT 1"},{"name":"VIASPORT 1 HD"},{"name":"VIASPORT 2"},{"name":"VIASPORT 2 HD"},{"name":"VIASPORT 3"},{"name":"VIASPORT 3 HD"},{"name":"MOTORVISION TV HD"},{"name":"BILKANALEN AUTO MOTOR OG SPORT TV HD"}],"VIAPLAY FILM":[{"name":"VIAPLAY FILM 1 FHD"},{"name":"VIAPLAY FILM 2 FHD"},{"name":"VIAPLAY FILM 3 FHD"},{"name":"VIAPLAY FILM 4 FHD"},{"name":"VIAPLAY FILM 5 FHD"},{"name":"VIAPLAY FILM 6 FHD"}],"NETFLIX FILM":[{"name":"NETFLIX FILM 1 FHD"},{"name":"NETFLIX FILM 2 FHD"},{"name":"NETFLIX FILM 3 FHD"}],"NETFLIX BARN":[{"name":"NETFLIX BARN 1 FHD"}],"HBO NORDIC FILM":[{"name":"HBO FILM 1 FHD"}],"DISNEY+ FILM":[{"name":"DISNEY+ FILM 1 FHD"},{"name":"DISNEY+ FILM 2 FHD"},{"name":"DISNEY+ FILM 3 FHD"},{"name":"DISNEY+ FILM 4 FHD"},{"name":"DISNEY+ FAMILIE 1 FHD"}],"DISNEY+ BARN":[{"name":"DISNEY+ BARN 1 FHD"},{"name":"DISNEY+ BARN 2 FHD"},{"name":"DISNEY+ BARN 3 FHD"},{"name":"DISNEY+ BARN 4 FHD"},{"name":"DISNEY+ BARN 5 FHD"}],"APPLE+ FILM":[{"name":"APPLE+ FILM 1 FHD"}],"APPLE+ BARN":[{"name":"APPLE+ BARN 1 FHD"}],"MARVEL FILM":[{"name":"MARVEL: ACTION FHD"},{"name":"MARVEL: ADVENTURES FHD"},{"name":"MARVEL: AVENGERS FHD"},{"name":"MARVEL: CAPTAIN AMERICA FHD"},{"name":"MARVEL: DEADPOOL FHD"},{"name":"MARVEL: IRON MAN FHD"},{"name":"MARVEL: THOR FHD"},{"name":"MARVEL: X-MEN FHD"},{"name":"VIAPLAY XSTRA 1 HD"},{"name":"VIAPLAY XSTRA 2 HD"},{"name":"VIAPLAY XSTRA 3 HD"},{"name":"VIAPLAY XSTRA 4 HD"},{"name":"VIAPLAY XSTRA 5 HD"},{"name":"VIAPLAY XSTRA 6 HD"},{"name":"VIAPLAY XSTRA 7 HD"},{"name":"VIAPLAY XSTRA 8 HD"},{"name":"VIAPLAY XSTRA 9 HD"},{"name":"VIAPLAY XSTRA 10 HD"},{"name":"VIAPLAY XSTRA 11 HD"},{"name":"VIAPLAY XSTRA 12 HD"},{"name":"VIAPLAY XSTRA 13 HD"},{"name":"VIAPLAY XSTRA 14 HD"},{"name":"VIAPLAY XSTRA 15 HD"},{"name":"VIAPLAY XSTRA 16 HD"},{"name":"VIAPLAY XSTRA 17 HD"},{"name":"VIAPLAY XSTRA 18 HD"},{"name":"VIAPLAY XSTRA 19 HD"},{"name":"VIAPLAY XSTRA 21 HD"},{"name":"VIAPLAY XSTRA 22 HD"},{"name":"VIAPLAY XSTRA 23 HD"},{"name":"VIAPLAY XSTRA 24 HD"},{"name":"VIAPLAY XSTRA 25 HD"},{"name":"VIAPLAY XSTRA 26 HD"},{"name":"VIAPLAY XSTRA 27 HD"},{"name":"VIAPLAY XSTRA 28 HD"},{"name":"VIAPLAY XSTRA 29 HD"},{"name":"VIAPLAY XSTRA 30 HD"},{"name":"VIAPLAY XSTRA 31 HD"},{"name":"VIAPLAY XSTRA 32 HD"},{"name":"VIAPLAY XSTRA 33 HD"},{"name":"VIAPLAY XSTRA 34 HD"},{"name":"VIAPLAY XSTRA 35 HD"},{"name":"VIAPLAY XSTRA 36 HD"},{"name":"VIAPLAY XSTRA 37 HD"},{"name":"VIAPLAY XSTRA 38 HD"},{"name":"VIAPLAY XSTRA 39 HD"},{"name":"VIAPLAY XSTRA 40 HD"},{"name":"VIAPLAY XSTRA 41 HD"},{"name":"VIAPLAY XSTRA 42 HD"},{"name":"VIAPLAY XSTRA 43 HD"},{"name":"VIAPLAY XSTRA 44 HD"},{"name":"VIAPLAY XSTRA 45 HD"},{"name":"VIAPLAY XSTRA 46 HD"},{"name":"VIAPLAY XSTRA 47 HD"},{"name":"VIAPLAY XSTRA 48 HD"},{"name":"VIAPLAY XSTRA 49 HD"}]}