[
  {"name": "BBC 1 HD"},
  {"name": "BBC 2 HD"},
  {"name": "BBC 3/CBBC HD"},
  {"name": "BBC 4/CBEEBIES HD"},
  {"name": "BBC SCOTLAND HD"},
  {"name": "BBC ONE SCOTLAND HD"},
  {"name": "ITV 1 HD"},
  {"name": "ITV 2 HD"},
  {"name": "ITV 3 HD"},
  {"name": "ITV 4 HD"},
  {"name": "ITV BE HD"},
  {"name": "GB NEWS HD"},
  {"name": "CHANNEL 4 HD"},
  {"name": "CHANNEL 5 HD"},
  {"name": "E4 HD"},
  {"name": "CBBC HD"},
  {"name": "4 SEVEN HD"},
  {"name": "ALIBI HD"},
  {"name": "BBC NEWS HD"},
  {"name": "BBC WORLD NEWS HD"},
  {"name": "BLOOMBERG HD"},
  {"name": "CNN HD"},
  {"name": "FRANCE 24 HD"},
  {"name": "SKY NEWS HD"},
  {"name": "FOOD NETWORK"},
  {"name": "HOME"},
  {"name": "BBC ALBA"},
  {"name": "BBC SCOTLAND"},
  {"name": "BBC ONE SCOTLAND"},
  {"name": "BBC ONE CAMBRIDGE"},
  {"name": "BBC ONE CHANNEL ISLANDS"},
  {"name": "BBC ONE EAST"},
  {"name": "BBC ONE EAST MIDLANDS"},
  {"name": "BBC ONE LONDON"},
  {"name": "BBC ONE NORTH EAST & CUMBRIA"},
  {"name": "BBC ONE NORTH WEST"},
  {"name": "BBC ONE NORTHEN ISLAND"},
  {"name": "BBC ONE OXFORD"},
  {"name": "BBC ONE SOUTH"},
  {"name": "BBC ONE SOUTH EAST"},
  {"name": "BBC ONE SOUTH WEST"},
  {"name": "BBC ONE WALES"},
  {"name": "BBC ONE WEST"},
  {"name": "BBC ONE WEST MIDLANDS"},
  {"name": "BBC ONE YORK"},
  {"name": "BBC ONE YORKSHIRE & LINCOLNSHIRE"},
  {"name": "BBC TWO ENGLAND"},
  {"name": "BBC TWO NORTHEN IRELAND"},
  {"name": "BBC TWO WALES"},
  {"name": "CHANNEL 4 MIDLANDS"},
  {"name": "CHANNEL 4 NORTH"},
  {"name": "CHANNEL 4 NORTHEN IRELAND"},
  {"name": "CHANNEL 4 SCOTLAND"},
  {"name": "CHANNEL 4 SOUTH AND EAST"},
  {"name": "ITV LONDON"},
  {"name": "ITV TYNE TEES"},
  {"name": "ITV ANGLIA EAST"},
  {"name": "ITV ANGLIA WEST"},
  {"name": "ITV CENTRAL EAST"},
  {"name": "ITV CENTRAL WEST"},
  {"name": "ITV GRANADA"},
  {"name": "ITV MERIDIAN EAST"},
  {"name": "ITV MERIDIAN NORTH"},
  {"name": "ITV MERIDIAN SOUTH"},
  {"name": "ITV TYNE TEES NORTH"},
  {"name": "ITV WESTCOUNTRY SOUTH WEST"},
  {"name": "ITV WESTCOUNTRY WEST"},
  {"name": "ITV YORKSHIRE EAST"},
  {"name": "ITV YORKSHIRE WEST"},
  {"name": "ITV BORDER"},
  {"name": "ITV WALES"},
  {"name": "STV"},
  {"name": "STV CENTRAL WEST"},
  {"name": "STV NORTH"},
  {"name": "BORDER SCOTLAND TV"},
  {"name": "CARTOON NETWORK HD"},
  {"name": "DISNEY CHANNEL HD"},
  {"name": "DISNEY JUNIOR HD"},
  {"name": "NICK HD"},
  {"name": "CBEEBIES HD"},
  {"name": "EDEN HD"},
  {"name": "GOLD HD"},
  {"name": "DAVE HD"},
  {"name": "E! ENTERTAINMENT HD"},
  {"name": "MORE 4 HD"},
  {"name": "QUEST HD"},
  {"name": "SKY MAX HD"},
  {"name": "SKY ATLANTIC HD"},
  {"name": "SKY ARTS HD"},
  {"name": "SKY WITNESS HD"},
  {"name": "SKY SHOWCASE HD"},
  {"name": "STV HD"},
  {"name": "UTV HD"},
  {"name": "UNIVERSAL HD"},
  {"name": "WATCH HD"},
  {"name": "TLC HD"},
  {"name": "COMEDY CENTRAL HD"},
  {"name": "SKY CINEMA ACTION HD"},
  {"name": "SKY CINEMA COMEDY HD"},
  {"name": "SKY CINEMA FAMILY HD"},
  {"name": "SKY CINEMA PREMIERE HD"},
  {"name": "SKY CINEMA GREATS HD"},
  {"name": "SKY CINEMA SCI-FI & HORROR HD"},
  {"name": "SKY CINEMA SUPERHEROES HD"},
  {"name": "SKY CINEMA THRILLER HD"},
  {"name": "SKY CINEMA DRAMA HD"},
  {"name": "SKY CINEMA HITS HD"},
  {"name": "SKY CINEMA ANIMATION HD"},
  {"name": "TCM HD"},
  {"name": "AMC HD"},
  {"name": "FILM 4 HD"},
  {"name": "MTV HD"},
  {"name": "MTV LIVE HD"},
  {"name": "SKY DOCUMENTARIES HD"},
  {"name": "DISCOVERY HD"},
  {"name": "NAT GEO HD"},
  {"name": "NAT GEO WILD HD"},
  {"name": "ANIMAL PLANET HD"},
  {"name": "CRIME&INVESTIGATION HD"},
  {"name": "HISTORY HD"},
  {"name": "HISTORY 2 HD"},
  {"name": "PARAMOUNT NETWORK HD"},
  {"name": "SYFY HD"},
  {"name": "SMITHSONIAN CHANNEL HD"},
  {"name": "SKY NATURE HD"},
  {"name": "SKY CRIME HD"},
  {"name": "BEIN SPORT HD"},
  {"name": "BEIN SPORTS NBA HD"},
  {"name": "BEIN SPORT NEWS HD"},
  {"name": "BEIN SPORTS PREMIUM 1 HD"},
  {"name": "BEIN SPORTS PREMIUM 2 HD"},
  {"name": "BEIN SPORTS PREMIUM 3 HD"},
  {"name": "BEIN SPORTS 1 HD"},
  {"name": "BEIN SPORTS 2 HD"},
  {"name": "BEIN SPORTS 3 HD"},
  {"name": "BEIN SPORTS 4 HD"},
  {"name": "BEIN SPORTS 5 HD"},
  {"name": "BEIN SPORTS 6 HD"},
  {"name": "BEIN SPORTS 7 HD"},
  {"name": "BEIN SPORTS XTRA 1 HD"},
  {"name": "BEIN SPORTS XTRA 2 HD"},
  {"name": "BEIN SPORTS 1 ENGLISH HD"},
  {"name": "BEIN SPORTS 2 ENGLISH HD"},
  {"name": "BEIN SPORTS 3 ENGLISH HD"},
  {"name": "BEIN SPORTS 1 FRENCH HD"},
  {"name": "SKY SPORTS NEWS HD"},
  {"name": "SKY SPORTS ACTION HD"},
  {"name": "SKY SPORTS FOOTBALL HD"},
  {"name": "SKY SPORTS MAIN EVENT HD"},
  {"name": "SKY SPORTS PREMIER LEAGUE HD"},
  {"name": "SKY SPORTS ARENA HD"},
  {"name": "SKY SPORTS CRICKET HD"},
  {"name": "SKY SPORTS F1 HD"},
  {"name": "SKY SPORTS GOLF HD"},
  {"name": "BT SPORTS ESPN HD"},
  {"name": "BT SPORTS 1 HD"},
  {"name": "BT SPORTS 2 HD"},
  {"name": "BT SPORTS 3 HD"},
  {"name": "CHELSEA TV HD"},
  {"name": "RANGERS FC TV HD"},
  {"name": "BOX NATION HD"},
  {"name": "SUPERSPORT VARIETY 1 HD"},
  {"name": "SUPERSPORT VARIETY 2 HD"},
  {"name": "SUPERSPORT VARIETY 3 HD"},
  {"name": "SUPERSPORT VARIETY 4 HD"},
  {"name": "SUPERSPORT FOOTBALL HD"},
  {"name": "SUPERSPORT PREMIER LEAGUE HD"},
  {"name": "SUPERSPORT LALIGA HD"},
  {"name": "SUPERSPORT TENNIS HD"},
  {"name": "SUPERSPORT RUGBY HD"},
  {"name": "SUPERSPORT CRICKET HD"},
  {"name": "SUPERSPORT GOLF HD"},
  {"name": "SUPERSPORT MOTOSPORT HD"},
  {"name": "SUPERSPORT EVENTS HD"},
  {"name": "SUPERSPORT PLAY HD"},
  {"name": "SUPERSPORT BLITZ HD"},
  {"name": "SUPERSPORT MAXIMO HD"}
]
